cartridge_braintree/__init__.py
cartridge_braintree/braintree_payment.py
cartridge_braintree/countries.py
cartridge_braintree/defaults.py
cartridge_braintree/forms.py
cartridge_braintree/urls.py
cartridge_braintree/utils.py
cartridge_braintree/locale/ar/LC_MESSAGES/django.po
cartridge_braintree/locale/cs/LC_MESSAGES/django.po
cartridge_braintree/locale/de/LC_MESSAGES/django.po
cartridge_braintree/locale/el/LC_MESSAGES/django.po
cartridge_braintree/locale/eo/LC_MESSAGES/django.po
cartridge_braintree/locale/es/LC_MESSAGES/django.po
cartridge_braintree/locale/et/LC_MESSAGES/django.po
cartridge_braintree/locale/fa/LC_MESSAGES/django.po
cartridge_braintree/locale/fi/LC_MESSAGES/django.po
cartridge_braintree/locale/fr/LC_MESSAGES/django.po
cartridge_braintree/locale/hr/LC_MESSAGES/django.po
cartridge_braintree/locale/it/LC_MESSAGES/django.po
cartridge_braintree/locale/ja/LC_MESSAGES/django.po
cartridge_braintree/locale/nb/LC_MESSAGES/django.po
cartridge_braintree/locale/nl/LC_MESSAGES/django.po
cartridge_braintree/locale/pl/LC_MESSAGES/django.po
cartridge_braintree/locale/pt_BR/LC_MESSAGES/django.po
cartridge_braintree/locale/pt_PT/LC_MESSAGES/django.po
cartridge_braintree/locale/ru/LC_MESSAGES/django.po
cartridge_braintree/locale/sk/LC_MESSAGES/django.po
cartridge_braintree/locale/sv/LC_MESSAGES/django.po
cartridge_braintree/locale/tr_TR/LC_MESSAGES/django.po
cartridge_braintree/locale/uk/LC_MESSAGES/django.po
cartridge_braintree/locale/zh_CN/LC_MESSAGES/django.po
cartridge_braintree/static/cartridge_braintree/css/checkout.css
cartridge_braintree/static/cartridge_braintree/js/jquery.payment.js
cartridge_braintree/static/cartridge_braintree/js/braintree-3.85.2/client.js
cartridge_braintree/static/cartridge_braintree/js/braintree-3.85.2/client.min.js
cartridge_braintree/static/cartridge_braintree/js/braintree-3.85.2/paypal-modal.js
cartridge_braintree/static/cartridge_braintree/js/braintree-3.85.2/paypal-modal.js.patch
cartridge_braintree-3.0.6.dist-info/LICENSE
cartridge_braintree-3.0.6.dist-info/WHEEL
cartridge_braintree-3.0.6.dist-info/METADATA
cartridge_braintree-3.0.6.dist-info/RECORD
