Metadata-Version: 2.1
Name: cartridge_braintree
Version: 3.0.6
Summary: Braintree Payments processing for Mezzanine/Cartridge
Keywords: django,mezzanine,cartridge,payment
Author-email: Henri Hulski <henri@yacoma.it>
Requires-Python: >=3.7
Classifier: Development Status :: 5 - Production/Stable
Classifier: Environment :: Web Environment
Classifier: Framework :: Django
Classifier: Framework :: Django :: 3.2
Classifier: Framework :: Django :: 4.0
Classifier: Intended Audience :: Developers
Classifier: License :: OSI Approved :: BSD License
Classifier: Operating System :: OS Independent
Classifier: Programming Language :: Python
Classifier: Programming Language :: Python :: 3
Classifier: Programming Language :: Python :: 3.7
Classifier: Programming Language :: Python :: 3.8
Classifier: Programming Language :: Python :: 3.9
Classifier: Programming Language :: Python :: 3.10
Classifier: Topic :: Internet :: WWW/HTTP
Classifier: Topic :: Internet :: WWW/HTTP :: Dynamic Content
Classifier: Topic :: Internet :: WWW/HTTP :: WSGI
Classifier: Topic :: Software Development :: Libraries :: Application Frameworks
Classifier: Topic :: Software Development :: Libraries :: Python Modules
Requires-Dist: braintree
Requires-Dist: cartridge >= 1.3
Requires-Dist: django >= 3.2.4, < 4.1
Requires-Dist: mezzanine >= 5.1
Requires-Dist: flake8 >= 3 ; extra == "codestyle"
Requires-Dist: black ; extra == "codestyle"
Requires-Dist: isort >= 5 ; extra == "codestyle"
Requires-Dist: pyupgrade >= 2 ; extra == "codestyle"
Requires-Dist: pyuca ; extra == "countries_utf8_sorting"
Project-URL: repository, https://github.com/henri-hulski/cartridge_braintree
Provides-Extra: codestyle
Provides-Extra: countries_utf8_sorting
